gnucash_portfolio/__init__.py
gnucash_portfolio/accounts.py
gnucash_portfolio/bookaggregate.py
gnucash_portfolio/currencies.py
gnucash_portfolio/metadata.py
gnucash_portfolio/pricesaggregate.py
gnucash_portfolio/scheduledtxaggregate.py
gnucash_portfolio/securitiesaggregate.py
gnucash_portfolio/splitsaggregate.py
gnucash_portfolio/transactionaggregate.py
gnucash_portfolio/actions/__init__.py
gnucash_portfolio/actions/find_report_settings.py
gnucash_portfolio/actions/get_vanguard_au_prices.py
gnucash_portfolio/actions/import_exchange_rates.py
gnucash_portfolio/actions/import_security_prices.py
gnucash_portfolio/actions/search_for_account.py
gnucash_portfolio/actions/security_analysis.py
gnucash_portfolio/actions/symbol_dividends.py
gnucash_portfolio/config/settings.json.template
gnucash_portfolio/lib/__init__.py
gnucash_portfolio/lib/aggregatebase.py
gnucash_portfolio/lib/csv_parser.py
gnucash_portfolio/lib/database.py
gnucash_portfolio/lib/datetimeutils.py
gnucash_portfolio/lib/fileutils.py
gnucash_portfolio/lib/generic.py
gnucash_portfolio/lib/messenger.py
gnucash_portfolio/lib/portfoliovalue.py
gnucash_portfolio/lib/settings.py
gnucash_portfolio/lib/templates.py
gnucash_portfolio/mappers/__init__.py
gnucash_portfolio/mappers/splitmapper.py
gnucash_portfolio/model/__init__.py
gnucash_portfolio/model/datetime_model.py
gnucash_portfolio/model/price_model.py
gnucash_portfolio/model/split_model.py
gnucash_portfolio/model/stock_model.py
gnucash_portfolio/reports/__init__.py
gnucash_portfolio/reports/portfolio_models.py
gnucash_portfolio/reports/portfolio_value.py
gnucash_portfolio/reports/security_info.py
gnucash_portfolio-1.6.2.dist-info/LICENSE
gnucash_portfolio-1.6.2.dist-info/METADATA
gnucash_portfolio-1.6.2.dist-info/WHEEL
gnucash_portfolio-1.6.2.dist-info/top_level.txt
gnucash_portfolio-1.6.2.dist-info/RECORD
