Metadata-Version: 2.1
Name: gnucash-portfolio
Version: 1.6.2
Summary: Portfolio tools for GnuCash
Home-page: https://github.com/MisterY/gnucash-portfolio
Author: Alen Siljak
Author-email: alen.siljak@gmx.com
License: GPL version 3
Keywords: personal finance gnucash portfolio tools
Platform: UNKNOWN
Classifier: Development Status :: 4 - Beta
Classifier: Intended Audience :: Developers
Classifier: License :: OSI Approved :: GNU General Public License v3 (GPLv3)
Classifier: Programming Language :: Python :: 3
Classifier: Programming Language :: Python :: 3.4
Classifier: Programming Language :: Python :: 3.5
Classifier: Programming Language :: Python :: 3.6
Requires-Python: >=3.0
Requires-Dist: PriceDb
Requires-Dist: pydatum
Requires-Dist: sqlalchemy
Requires-Dist: piecash
Requires-Dist: python-dateutil
